natorbs/__init__.py
natorbs/_version.py
natorbs/diff.py
natorbs/moldata.py
natorbs/mulliken.py
natorbs/mutual_overlaps.py
natorbs/natural.py
natorbs-1.0.2.data/data/share/doc/natorbs/LICENSE.txt
natorbs-1.0.2.data/data/share/doc/natorbs/README.rst
natorbs-1.0.2.data/data/share/man/man1/natorbs.1
natorbs-1.0.2.data/scripts/natorbs
natorbs-1.0.2.dist-info/LICENSE.txt
natorbs-1.0.2.dist-info/METADATA
natorbs-1.0.2.dist-info/WHEEL
natorbs-1.0.2.dist-info/top_level.txt
natorbs-1.0.2.dist-info/RECORD
