Metadata-Version: 2.1
Name: natorbs
Version: 1.0.2
Summary: Quantum-chemical utility for computing natural orbitals
Home-page: https://tungsten.ch.uj.edu.pl/~mradon/natorbs
Download-URL: https://tungsten.ch.uj.edu.pl/downloadmanager/click.php?id=natorbs
Author: Mariusz Radon
Author-email: mradon@chemia.uj.edu.pl
License: BSD-3-Clause
Keywords: quantum chemistry,natural orbitals,nocv
Platform: UNKNOWN
Classifier: Development Status :: 5 - Production/Stable
Classifier: Environment :: Console
Classifier: Intended Audience :: Science/Research
Classifier: License :: OSI Approved :: BSD License
Classifier: Natural Language :: English
Classifier: Programming Language :: Python :: 3
Classifier: Programming Language :: Python :: 3.6
Classifier: Programming Language :: Python :: 3.7
Classifier: Programming Language :: Python :: 3.8
Requires-Python: >=3.6
License-File: LICENSE.txt
Requires-Dist: numpy
Requires-Dist: cclib (>=1.7)
